data2rdf/__init__.py
data2rdf/config.py
data2rdf/utils.py
data2rdf/warnings.py
data2rdf/models/__init__.py
data2rdf/models/base.py
data2rdf/models/graph.py
data2rdf/models/mapping.py
data2rdf/models/utils.py
data2rdf/modes/__init__.py
data2rdf/parsers/__init__.py
data2rdf/parsers/base.py
data2rdf/parsers/csv.py
data2rdf/parsers/excel.py
data2rdf/parsers/json.py
data2rdf/parsers/utils.py
data2rdf/pipelines/__init__.py
data2rdf/pipelines/main.py
data2rdf/qudt/__init__.py
data2rdf/qudt/utils.py
data2rdf-2.5.0.dist-info/licenses/LICENSE
tests/__init__.py
tests/test_utils.py
tests/abox/__init__.py
tests/abox/test_models.py
tests/abox/utils.py
tests/abox/csv_empty_rows/__init__.py
tests/abox/csv_empty_rows/test_parser.py
tests/abox/csv_empty_rows/test_pipeline.py
tests/abox/csv_empty_rows/output/__init__.py
tests/abox/csv_pipeline_test/__init__.py
tests/abox/csv_pipeline_test/test_parser.py
tests/abox/csv_pipeline_test/test_pipeline.py
tests/abox/csv_pipeline_test/input/__init__.py
tests/abox/csv_without_header/__init__.py
tests/abox/csv_without_header/test_parser.py
tests/abox/csv_without_header/test_pipeline.py
tests/abox/csv_without_header/input/__init__.py
tests/abox/csv_without_header/input/data/__init__.py
tests/abox/csv_without_header/input/data/test.csv
tests/abox/csv_without_header/input/mapping/__init__.py
tests/abox/csv_without_header/output/__init__.py
tests/abox/dict_custom_properties/__init__.py
tests/abox/dict_custom_properties/test_pipeline.py
tests/abox/json_custom_relations/__init__.py
tests/abox/json_custom_relations/test_json_custom_relations.py
tests/abox/json_multiple_iris/__init__.py
tests/abox/json_multiple_iris/test_multiple_iris.py
tests/abox/json_pipeline_test/__init__.py
tests/abox/json_pipeline_test/test_parser.py
tests/abox/json_pipeline_test/test_pipeline.py
tests/abox/xls_custom_relations/__init__.py
tests/abox/xls_custom_relations/test_xlsx_custom_relations.py
tests/abox/xls_pipeline_test/__init__.py
tests/abox/xls_pipeline_test/test_parser.py
data2rdf-2.5.0.dist-info/METADATA
data2rdf-2.5.0.dist-info/WHEEL
data2rdf-2.5.0.dist-info/top_level.txt
data2rdf-2.5.0.dist-info/RECORD
