Metadata-Version: 2.4
Name: data2rdf
Version: 2.5.0
Summary: A generic pipeline that can be used to map raw data to RDF.
Home-page: https://github.com/MI-FraunhoferIWM/data2rdf
Author: Paul Zierep, Yoav Nahshon, Pablo de Andres, Deepu Krishnareddy, Matthias Büschelberger
Author-email: matthias.bueschelberger@iwm.fraunhofer.de, yoav.nahshon@iwm.fraunhofer.de, pablo.de.andres@iwm.fraunhofer.de, deepu.krishnareddy@iwm.fraunhofer.de, matthias.bueschelberger@iwm.fraunhofer.de
License: BSD-3-Clause
Classifier: Development Status :: 2 - Pre-Alpha
Classifier: License :: OSI Approved :: BSD License
Classifier: Programming Language :: Python :: 3
Classifier: Programming Language :: Python :: 3 :: Only
Classifier: Programming Language :: Python :: Implementation :: CPython
Requires-Python: >=3.9
License-File: LICENSE
Requires-Dist: jsonpath-ng~=1.6.1
Requires-Dist: lru-cache<1
Requires-Dist: openpyxl<4,>=3
Requires-Dist: pandas<3,>=2
Requires-Dist: pydantic<3,>=2
Requires-Dist: pydantic-settings
Requires-Dist: rdflib<7,>=6
Requires-Dist: requests
Requires-Dist: tables<4,>=3
Provides-Extra: dev
Requires-Dist: bumpver==2021.1114; extra == "dev"
Requires-Dist: dunamai==1.7.0; extra == "dev"
Provides-Extra: docs
Requires-Dist: html5lib==1.1; extra == "docs"
Requires-Dist: ipython==8.12.3; extra == "docs"
Requires-Dist: jinja2==3.1.3; extra == "docs"
Requires-Dist: jupyter==1.0.0; extra == "docs"
Requires-Dist: myst-parser==2.0.0; extra == "docs"
Requires-Dist: nbsphinx==0.9.3; extra == "docs"
Requires-Dist: sphinx==6.2.1; extra == "docs"
Requires-Dist: sphinx-autobuild==2021.3.14; extra == "docs"
Requires-Dist: sphinx-book-theme==1.0.1; extra == "docs"
Requires-Dist: sphinx-copybutton==0.5.2; extra == "docs"
Requires-Dist: sphinx-design==0.5.0; extra == "docs"
Requires-Dist: sphinxcontrib-redoc==1.6.0; extra == "docs"
Provides-Extra: pre-commit
Requires-Dist: pre-commit==2.15.0; extra == "pre-commit"
Provides-Extra: tests
Requires-Dist: pytest==8.2.2; extra == "tests"
Requires-Dist: pytest-cov==5.0.0; extra == "tests"
Dynamic: license-file
